update_plex_music_album_covers.py
update_plex_music_album_covers-0.1.2.dist-info/LICENSE
update_plex_music_album_covers-0.1.2.dist-info/METADATA
update_plex_music_album_covers-0.1.2.dist-info/WHEEL
update_plex_music_album_covers-0.1.2.dist-info/entry_points.txt
update_plex_music_album_covers-0.1.2.dist-info/top_level.txt
update_plex_music_album_covers-0.1.2.dist-info/RECORD
