Metadata-Version: 2.1
Name: update-plex-music-album-covers
Version: 0.1.2
Summary: Update Plex music album covers to the corresponding front covers embedded in your MP3 files
Home-page: https://github.com/lightrush/update-plex-music-album-covers
Author: Nicolay Doytchev
Author-email: self@ndoytchev.com
License: UNKNOWN
Keywords: update plex music album covers
Platform: UNKNOWN
Classifier: Programming Language :: Python :: 3
Classifier: License :: OSI Approved :: GNU General Public License v3 (GPLv3)
Classifier: Operating System :: OS Independent
Classifier: Development Status :: 3 - Alpha
Requires-Python: >=3.6
Requires-Dist: Click
Requires-Dist: mutagen
Requires-Dist: plexapi
